pycfrl/__init__.py
pycfrl/requirements.txt
pycfrl/agents/__init__.py
pycfrl/agents/agents.py
pycfrl/environment/__init__.py
pycfrl/environment/environment.py
pycfrl/evaluation/__init__.py
pycfrl/evaluation/evaluation.py
pycfrl/fqe/__init__.py
pycfrl/fqe/fqe.py
pycfrl/olds/agents_20250830.py
pycfrl/olds/agents_20250905.py
pycfrl/olds/agents_old.py
pycfrl/olds/base_models_20250830.py
pycfrl/olds/base_models_20250905.py
pycfrl/olds/base_models_old.py
pycfrl/olds/environment_20250905.py
pycfrl/olds/environment_old.py
pycfrl/olds/evaluation_20250830.py
pycfrl/olds/evaluation_20250905.py
pycfrl/olds/evaluation_old.py
pycfrl/olds/fqe_20250830.py
pycfrl/olds/fqe_20250905.py
pycfrl/olds/fqe_old.py
pycfrl/olds/preprocessor_20250905.py
pycfrl/olds/preprocessor_old.py
pycfrl/preprocessor/__init__.py
pycfrl/preprocessor/preprocessor.py
pycfrl/reader/__init__.py
pycfrl/reader/reader.py
pycfrl/utils/base_models.py
pycfrl/utils/custom_errors.py
pycfrl-0.3.0.dist-info/METADATA
pycfrl-0.3.0.dist-info/WHEEL
pycfrl-0.3.0.dist-info/licenses/LICENSE
pycfrl-0.3.0.dist-info/RECORD
