Metadata-Version: 2.4
Name: pycfrl
Version: 0.3.0
Summary: The PyCFRL package implements algorithms to ensure counterfactual fairness in reinforcement learning and provides tools for evaluating the value and counterfactual fairness of reinforcement learning policies.
Project-URL: Documentation, https://cfrl-documentation.netlify.app/
Project-URL: Repository, https://github.com/JianhanZhang/CFRL
Author-email: Jianhan Zhang <jhzhang0621@gmail.com>
Maintainer-email: Jianhan Zhang <jhzhang0621@gmail.com>
License: MIT License
License-File: LICENSE
Keywords: counterfactual fairness,reinforcement-learning
Classifier: Development Status :: 4 - Beta
Classifier: License :: OSI Approved :: MIT License
Classifier: Operating System :: OS Independent
Classifier: Programming Language :: Python :: 3
Requires-Python: >=3.10
Requires-Dist: gymnasium>=0.26.0
Requires-Dist: numpy>=1.23.0
Requires-Dist: pandas>=1.5.0
Requires-Dist: scikit-learn~=1.7.0
Requires-Dist: torch~=2.4.1
Requires-Dist: tqdm~=4.66.2
